{
    "defaultSeverity": "error",
    "extends": [
        "tslint:recommended"
    ],
    "jsRules": {},
    "rules": {
        "trailing-comma": [
            false
        ],
        "interface-name": [
            true,
            "never-prefix"
        ],
        "object-literal-sort-keys": false,
        "max-classes-per-file": [
            true,
            5,
            "exclude-class-expressions"
        ],
        "no-namespace": false,
        "unified-signatures": false,
        "only-arrow-functions": false,
        "variable-name": {
            "options": [
                "require-const-for-all-caps",
                "check-format",
                "allow-leading-underscore",
                "allow-pascal-case"
            ]
        }
    },
    "rulesDirectory": []
}